requirements.txt
acedatacloud_scaffold/__init__.py
acedatacloud_scaffold/__version__.py
acedatacloud_scaffold/settings.py
acedatacloud_scaffold/controllers/__init__.py
acedatacloud_scaffold/controllers/base.py
acedatacloud_scaffold/exceptions/__init__.py
acedatacloud_scaffold/exceptions/api_not_implemented.py
acedatacloud_scaffold/exceptions/bad_request.py
acedatacloud_scaffold/exceptions/base.py
acedatacloud_scaffold/exceptions/invalid_token.py
acedatacloud_scaffold/exceptions/no_api.py
acedatacloud_scaffold/exceptions/no_token.py
acedatacloud_scaffold/exceptions/token_mismatched.py
acedatacloud_scaffold/exceptions/too_many_requests.py
acedatacloud_scaffold/exceptions/used_up.py
acedatacloud_scaffold/handlers/__init__.py
acedatacloud_scaffold/handlers/base.py
acedatacloud_scaffold/handlers/callback.py
acedatacloud_scaffold/handlers/health.py
acedatacloud_scaffold/handlers/hybrid.py
acedatacloud_scaffold/mixins/__init__.py
acedatacloud_scaffold/mixins/forward.py
acedatacloud_scaffold/mixins/log.py
acedatacloud_scaffold-0.8.3.dist-info/METADATA
acedatacloud_scaffold-0.8.3.dist-info/WHEEL
acedatacloud_scaffold-0.8.3.dist-info/top_level.txt
acedatacloud_scaffold-0.8.3.dist-info/RECORD
